huaweicloudsdkvcm/__init__.py
huaweicloudsdkvcm/v2/__init__.py
huaweicloudsdkvcm/v2/vcm_async_client.py
huaweicloudsdkvcm/v2/vcm_client.py
huaweicloudsdkvcm/v2/model/__init__.py
huaweicloudsdkvcm/v2/model/audio_input_data.py
huaweicloudsdkvcm/v2/model/audio_output.py
huaweicloudsdkvcm/v2/model/audio_output_hosting.py
huaweicloudsdkvcm/v2/model/audio_output_hosting_obs.py
huaweicloudsdkvcm/v2/model/audio_output_obs.py
huaweicloudsdkvcm/v2/model/audio_response_output.py
huaweicloudsdkvcm/v2/model/audio_response_output_hosting.py
huaweicloudsdkvcm/v2/model/audio_service_config.py
huaweicloudsdkvcm/v2/model/audio_service_config_common.py
huaweicloudsdkvcm/v2/model/check_audio_job_request.py
huaweicloudsdkvcm/v2/model/check_audio_job_response.py
huaweicloudsdkvcm/v2/model/check_audio_job_response_body.py
huaweicloudsdkvcm/v2/model/check_audio_job_response_body_input.py
huaweicloudsdkvcm/v2/model/check_video_job_request.py
huaweicloudsdkvcm/v2/model/check_video_job_response.py
huaweicloudsdkvcm/v2/model/create_audio_job_request.py
huaweicloudsdkvcm/v2/model/create_audio_job_request_body.py
huaweicloudsdkvcm/v2/model/create_audio_job_request_body_input.py
huaweicloudsdkvcm/v2/model/create_audio_job_response.py
huaweicloudsdkvcm/v2/model/create_audio_job_response_body.py
huaweicloudsdkvcm/v2/model/create_video_job_req.py
huaweicloudsdkvcm/v2/model/create_video_job_req_input.py
huaweicloudsdkvcm/v2/model/create_video_job_request.py
huaweicloudsdkvcm/v2/model/create_video_job_response.py
huaweicloudsdkvcm/v2/model/create_video_job_response_body.py
huaweicloudsdkvcm/v2/model/delete_demo_info_request.py
huaweicloudsdkvcm/v2/model/delete_demo_info_response.py
huaweicloudsdkvcm/v2/model/delete_video_job_request.py
huaweicloudsdkvcm/v2/model/delete_video_job_response.py
huaweicloudsdkvcm/v2/model/input_data.py
huaweicloudsdkvcm/v2/model/input_vcn.py
huaweicloudsdkvcm/v2/model/list_audio_jobs_request.py
huaweicloudsdkvcm/v2/model/list_audio_jobs_response.py
huaweicloudsdkvcm-3.1.184.dist-info/METADATA
huaweicloudsdkvcm-3.1.184.dist-info/WHEEL
huaweicloudsdkvcm-3.1.184.dist-info/licenses/LICENSE
huaweicloudsdkvcm-3.1.184.dist-info/RECORD
